prettyerr/__init__.py
prettyerr/py.typed
prettyerr-0.0.3.dist-info/METADATA
prettyerr-0.0.3.dist-info/WHEEL
prettyerr-0.0.3.dist-info/RECORD
