Metadata-Version: 2.4
Name: prettyerr
Version: 0.0.3
Summary: Pretty error messages
Project-URL: Repository, https://github.com/david-andrew/prettyerr
Author-email: David Samson <david.andrew.engineer@gmail.com>
Classifier: Programming Language :: Python :: 3
Classifier: Programming Language :: Python :: 3.10
Classifier: Programming Language :: Python :: 3.11
Classifier: Programming Language :: Python :: 3.12
Classifier: Programming Language :: Python :: 3.13
Classifier: Programming Language :: Python :: 3.14
Requires-Python: >=3.10
